{
  "Valgresultater": {
    "AfstemningsomraadeId": "703386",
    "Optaellingstype": "Fintaelling",
    "IndenforParti": [
      {
        "PartiId": "A",
        "Partistemmer": 323,
        "Kandidater": [
          {
            "KandidatId": "588",
            "Stemmer": 4
          },
          {
            "KandidatId": "589",
            "Stemmer": 89
          },
          {
            "KandidatId": "590",
            "Stemmer": 1
          },
          {
            "KandidatId": "591",
            "Stemmer": 0
          },
          {
            "KandidatId": "592",
            "Stemmer": 25
          },
          {
            "KandidatId": "593",
            "Stemmer": 7
          },
          {
            "KandidatId": "594",
            "Stemmer": 4
          },
          {
            "KandidatId": "595",
            "Stemmer": 33
          },
          {
            "KandidatId": "596",
            "Stemmer": 11
          },
          {
            "KandidatId": "597",
            "Stemmer": 38
          },
          {
            "KandidatId": "598",
            "Stemmer": 36
          },
          {
            "KandidatId": "599",
            "Stemmer": 38
          }
        ]
      },
      {
        "PartiId": "B",
        "Partistemmer": 164,
        "Kandidater": [
          {
            "KandidatId": "1440",
            "Stemmer": 2
          },
          {
            "KandidatId": "1441",
            "Stemmer": 11
          },
          {
            "KandidatId": "1442",
            "Stemmer": 11
          },
          {
            "KandidatId": "1443",
            "Stemmer": 1
          },
          {
            "KandidatId": "1444",
            "Stemmer": 9
          },
          {
            "KandidatId": "1445",
            "Stemmer": 14
          },
          {
            "KandidatId": "1446",
            "Stemmer": 5
          },
          {
            "KandidatId": "1447",
            "Stemmer": 3
          },
          {
            "KandidatId": "1448",
            "Stemmer": 1
          },
          {
            "KandidatId": "1449",
            "Stemmer": 45
          },
          {
            "KandidatId": "1450",
            "Stemmer": 83
          },
          {
            "KandidatId": "1451",
            "Stemmer": 40
          }
        ]
      },
      {
        "PartiId": "C",
        "Partistemmer": 82,
        "Kandidater": [
          {
            "KandidatId": "2285",
            "Stemmer": 2
          },
          {
            "KandidatId": "2286",
            "Stemmer": 4
          },
          {
            "KandidatId": "2287",
            "Stemmer": 4
          },
          {
            "KandidatId": "2288",
            "Stemmer": 16
          },
          {
            "KandidatId": "2289",
            "Stemmer": 0
          },
          {
            "KandidatId": "2290",
            "Stemmer": 14
          },
          {
            "KandidatId": "2291",
            "Stemmer": 9
          },
          {
            "KandidatId": "2292",
            "Stemmer": 0
          },
          {
            "KandidatId": "2293",
            "Stemmer": 2
          },
          {
            "KandidatId": "2294",
            "Stemmer": 1
          },
          {
            "KandidatId": "2295",
            "Stemmer": 0
          },
          {
            "KandidatId": "2296",
            "Stemmer": 0
          }
        ]
      },
      {
        "PartiId": "D",
        "Partistemmer": 32,
        "Kandidater": [
          {
            "KandidatId": "3109",
            "Stemmer": 0
          },
          {
            "KandidatId": "3110",
            "Stemmer": 6
          },
          {
            "KandidatId": "3111",
            "Stemmer": 1
          },
          {
            "KandidatId": "3112",
            "Stemmer": 1
          },
          {
            "KandidatId": "3113",
            "Stemmer": 1
          }
        ]
      },
      {
        "PartiId": "F",
        "Partistemmer": 215,
        "Kandidater": [
          {
            "KandidatId": "3789",
            "Stemmer": 8
          },
          {
            "KandidatId": "3790",
            "Stemmer": 4
          },
          {
            "KandidatId": "3791",
            "Stemmer": 27
          },
          {
            "KandidatId": "3792",
            "Stemmer": 3
          },
          {
            "KandidatId": "3793",
            "Stemmer": 22
          },
          {
            "KandidatId": "3794",
            "Stemmer": 7
          },
          {
            "KandidatId": "3795",
            "Stemmer": 5
          },
          {
            "KandidatId": "3796",
            "Stemmer": 19
          },
          {
            "KandidatId": "3797",
            "Stemmer": 0
          },
          {
            "KandidatId": "3798",
            "Stemmer": 2
          },
          {
            "KandidatId": "3799",
            "Stemmer": 199
          },
          {
            "KandidatId": "3800",
            "Stemmer": 2
          }
        ]
      },
      {
        "PartiId": "I",
        "Partistemmer": 174,
        "Kandidater": [
          {
            "KandidatId": "4625",
            "Stemmer": 20
          },
          {
            "KandidatId": "4626",
            "Stemmer": 2
          },
          {
            "KandidatId": "4627",
            "Stemmer": 0
          },
          {
            "KandidatId": "4628",
            "Stemmer": 0
          },
          {
            "KandidatId": "4629",
            "Stemmer": 5
          },
          {
            "KandidatId": "4630",
            "Stemmer": 2
          },
          {
            "KandidatId": "4631",
            "Stemmer": 3
          },
          {
            "KandidatId": "4632",
            "Stemmer": 29
          },
          {
            "KandidatId": "4633",
            "Stemmer": 3
          }
        ]
      },
      {
        "PartiId": "K",
        "Partistemmer": 9,
        "Kandidater": [
          {
            "KandidatId": "5336",
            "Stemmer": 0
          },
          {
            "KandidatId": "5337",
            "Stemmer": 0
          },
          {
            "KandidatId": "5338",
            "Stemmer": 1
          },
          {
            "KandidatId": "5339",
            "Stemmer": 0
          },
          {
            "KandidatId": "5340",
            "Stemmer": 1
          }
        ]
      },
      {
        "PartiId": "M",
        "Partistemmer": 229,
        "Kandidater": [
          {
            "KandidatId": "5868",
            "Stemmer": 8
          },
          {
            "KandidatId": "5869",
            "Stemmer": 7
          },
          {
            "KandidatId": "5870",
            "Stemmer": 20
          },
          {
            "KandidatId": "5871",
            "Stemmer": 2
          },
          {
            "KandidatId": "5872",
            "Stemmer": 1
          },
          {
            "KandidatId": "5873",
            "Stemmer": 14
          },
          {
            "KandidatId": "5874",
            "Stemmer": 8
          },
          {
            "KandidatId": "5875",
            "Stemmer": 1
          },
          {
            "KandidatId": "5876",
            "Stemmer": 30
          }
        ]
      },
      {
        "PartiId": "O",
        "Partistemmer": 37,
        "Kandidater": [
          {
            "KandidatId": "6441",
            "Stemmer": 0
          },
          {
            "KandidatId": "6442",
            "Stemmer": 1
          },
          {
            "KandidatId": "6443",
            "Stemmer": 2
          },
          {
            "KandidatId": "6444",
            "Stemmer": 0
          },
          {
            "KandidatId": "6445",
            "Stemmer": 3
          },
          {
            "KandidatId": "6446",
            "Stemmer": 0
          }
        ]
      },
      {
        "PartiId": "Q",
        "Partistemmer": 79,
        "Kandidater": [
          {
            "KandidatId": "6935",
            "Stemmer": 0
          },
          {
            "KandidatId": "6936",
            "Stemmer": 0
          },
          {
            "KandidatId": "6937",
            "Stemmer": 1
          },
          {
            "KandidatId": "6938",
            "Stemmer": 1
          },
          {
            "KandidatId": "6939",
            "Stemmer": 1
          },
          {
            "KandidatId": "6940",
            "Stemmer": 2
          },
          {
            "KandidatId": "6941",
            "Stemmer": 9
          },
          {
            "KandidatId": "6942",
            "Stemmer": 192
          }
        ]
      },
      {
        "PartiId": "V",
        "Partistemmer": 162,
        "Kandidater": [
          {
            "KandidatId": "7552",
            "Stemmer": 20
          },
          {
            "KandidatId": "7553",
            "Stemmer": 10
          },
          {
            "KandidatId": "7554",
            "Stemmer": 1
          },
          {
            "KandidatId": "7555",
            "Stemmer": 1
          },
          {
            "KandidatId": "7556",
            "Stemmer": 1
          },
          {
            "KandidatId": "7557",
            "Stemmer": 28
          },
          {
            "KandidatId": "7558",
            "Stemmer": 35
          },
          {
            "KandidatId": "7559",
            "Stemmer": 14
          },
          {
            "KandidatId": "7560",
            "Stemmer": 1
          },
          {
            "KandidatId": "7561",
            "Stemmer": 0
          },
          {
            "KandidatId": "7562",
            "Stemmer": 0
          },
          {
            "KandidatId": "7563",
            "Stemmer": 0
          }
        ]
      },
      {
        "PartiId": "Æ",
        "Partistemmer": 36,
        "Kandidater": [
          {
            "KandidatId": "9166",
            "Stemmer": 1
          },
          {
            "KandidatId": "9167",
            "Stemmer": 1
          }
        ]
      },
      {
        "PartiId": "Ø",
        "Partistemmer": 527,
        "Kandidater": [
          {
            "KandidatId": "9747",
            "Stemmer": 5
          },
          {
            "KandidatId": "9748",
            "Stemmer": 37
          },
          {
            "KandidatId": "9749",
            "Stemmer": 5
          },
          {
            "KandidatId": "9750",
            "Stemmer": 1
          },
          {
            "KandidatId": "9751",
            "Stemmer": 4
          },
          {
            "KandidatId": "9752",
            "Stemmer": 14
          },
          {
            "KandidatId": "9753",
            "Stemmer": 27
          },
          {
            "KandidatId": "9754",
            "Stemmer": 55
          },
          {
            "KandidatId": "9755",
            "Stemmer": 31
          },
          {
            "KandidatId": "9756",
            "Stemmer": 1
          },
          {
            "KandidatId": "9757",
            "Stemmer": 268
          },
          {
            "KandidatId": "9758",
            "Stemmer": 244
          }
        ]
      },
      {
        "PartiId": "Å",
        "Partistemmer": 309,
        "Kandidater": [
          {
            "KandidatId": "8507",
            "Stemmer": 1
          },
          {
            "KandidatId": "8508",
            "Stemmer": 10
          },
          {
            "KandidatId": "8509",
            "Stemmer": 1
          },
          {
            "KandidatId": "8510",
            "Stemmer": 76
          },
          {
            "KandidatId": "8511",
            "Stemmer": 284
          },
          {
            "KandidatId": "8512",
            "Stemmer": 5
          },
          {
            "KandidatId": "8513",
            "Stemmer": 0
          },
          {
            "KandidatId": "8514",
            "Stemmer": 8
          },
          {
            "KandidatId": "8515",
            "Stemmer": 5
          },
          {
            "KandidatId": "8516",
            "Stemmer": 3
          },
          {
            "KandidatId": "8517",
            "Stemmer": 6
          },
          {
            "KandidatId": "8518",
            "Stemmer": 11
          },
          {
            "KandidatId": "8519",
            "Stemmer": 14
          }
        ]
      },
      {
        "PartiId": "(Uden for parti)",
        "Partistemmer": 0,
        "Kandidater": [
          {
            "KandidatId": "75",
            "Stemmer": 8
          },
          {
            "KandidatId": "76",
            "Stemmer": 3
          }
        ]
      }
    ],
    "KandidaterUdenforParti": []
  }
}