{
  "Valgresultater": {
    "AfstemningsomraadeId": "709148",
    "Optaellingstype": "Foreløbig",
    "IndenforParti": [
      {
        "PartiId": "Ø",
        "Partistemmer": 6,
        "Kandidater": []
      },
      {
        "PartiId": "C",
        "Partistemmer": 11,
        "Kandidater": []
      },
      {
        "PartiId": "V",
        "Partistemmer": 112,
        "Kandidater": []
      },
      {
        "PartiId": "O",
        "Partistemmer": 54,
        "Kandidater": []
      },
      {
        "PartiId": "F",
        "Partistemmer": 10,
        "Kandidater": []
      },
      {
        "PartiId": "B",
        "Partistemmer": 8,
        "Kandidater": []
      },
      {
        "PartiId": "Å",
        "Partistemmer": 2,
        "Kandidater": []
      },
      {
        "PartiId": "I",
        "Partistemmer": 17,
        "Kandidater": []
      },
      {
        "PartiId": "D",
        "Partistemmer": 1,
        "Kandidater": []
      },
      {
        "PartiId": "A",
        "Partistemmer": 60,
        "Kandidater": []
      }
    ],
    "KandidaterUdenforParti": []
  }
}