{
  "Valg": {
    "OpstillingskredsId": "403629",
    "Partier": [
      {
        "PartiId": "A",
        "Stemmer": 14143
      },
      {
        "PartiId": "B",
        "Stemmer": 2631
      },
      {
        "PartiId": "C",
        "Stemmer": 3036
      },
      {
        "PartiId": "D",
        "Stemmer": 1585
      },
      {
        "PartiId": "F",
        "Stemmer": 7043
      },
      {
        "PartiId": "I",
        "Stemmer": 4851
      },
      {
        "PartiId": "K",
        "Stemmer": 117
      },
      {
        "PartiId": "M",
        "Stemmer": 7218
      },
      {
        "PartiId": "O",
        "Stemmer": 1460
      },
      {
        "PartiId": "Q",
        "Stemmer": 340
      },
      {
        "PartiId": "V",
        "Stemmer": 6924
      },
      {
        "PartiId": "Æ",
        "Stemmer": 2590
      },
      {
        "PartiId": "Ø",
        "Stemmer": 2861
      },
      {
        "PartiId": "Å",
        "Stemmer": 1739
      },
      {
        "PartiId": "(Uden for parti)",
        "Stemmer": 64
      }
    ]
  }
}