{
  "Valgresultater": {
    "AfstemningsomraadeId": "702034",
    "Optaellingstype": "Foreløbig",
    "IndenforParti": [
      {
        "PartiId": "I",
        "Partistemmer": 32,
        "Kandidater": []
      },
      {
        "PartiId": "V",
        "Partistemmer": 164,
        "Kandidater": []
      },
      {
        "PartiId": "O",
        "Partistemmer": 18,
        "Kandidater": []
      },
      {
        "PartiId": "B",
        "Partistemmer": 89,
        "Kandidater": []
      },
      {
        "PartiId": "Å",
        "Partistemmer": 11,
        "Kandidater": []
      },
      {
        "PartiId": "C",
        "Partistemmer": 49,
        "Kandidater": []
      },
      {
        "PartiId": "Ø",
        "Partistemmer": 121,
        "Kandidater": []
      },
      {
        "PartiId": "M",
        "Partistemmer": 11,
        "Kandidater": []
      },
      {
        "PartiId": "A",
        "Partistemmer": 460,
        "Kandidater": []
      },
      {
        "PartiId": "F",
        "Partistemmer": 288,
        "Kandidater": []
      }
    ],
    "KandidaterUdenforParti": []
  }
}