{
  "Valgresultater": {
    "AfstemningsomraadeId": "749377",
    "Optaellingstype": "Foreløbig",
    "IndenforParti": [
      {
        "PartiId": "B",
        "Partistemmer": 56,
        "Kandidater": []
      },
      {
        "PartiId": "O",
        "Partistemmer": 457,
        "Kandidater": []
      },
      {
        "PartiId": "M",
        "Partistemmer": 26,
        "Kandidater": []
      },
      {
        "PartiId": "A",
        "Partistemmer": 939,
        "Kandidater": []
      },
      {
        "PartiId": "C",
        "Partistemmer": 301,
        "Kandidater": []
      },
      {
        "PartiId": "Ø",
        "Partistemmer": 387,
        "Kandidater": []
      },
      {
        "PartiId": "V",
        "Partistemmer": 876,
        "Kandidater": []
      },
      {
        "PartiId": "F",
        "Partistemmer": 416,
        "Kandidater": []
      },
      {
        "PartiId": "Å",
        "Partistemmer": 14,
        "Kandidater": []
      },
      {
        "PartiId": "I",
        "Partistemmer": 180,
        "Kandidater": []
      }
    ],
    "KandidaterUdenforParti": []
  }
}