{
  "Valgresultater": {
    "AfstemningsomraadeId": "701580",
    "Optaellingstype": "Fintaelling",
    "IndenforParti": [
      {
        "PartiId": "A",
        "Partistemmer": 919,
        "Kandidater": [
          {
            "KandidatId": "478",
            "Stemmer": 11
          },
          {
            "KandidatId": "479",
            "Stemmer": 177
          },
          {
            "KandidatId": "480",
            "Stemmer": 16
          },
          {
            "KandidatId": "481",
            "Stemmer": 5
          },
          {
            "KandidatId": "482",
            "Stemmer": 47
          },
          {
            "KandidatId": "483",
            "Stemmer": 9
          },
          {
            "KandidatId": "484",
            "Stemmer": 3
          },
          {
            "KandidatId": "485",
            "Stemmer": 45
          },
          {
            "KandidatId": "486",
            "Stemmer": 21
          },
          {
            "KandidatId": "487",
            "Stemmer": 89
          },
          {
            "KandidatId": "488",
            "Stemmer": 274
          },
          {
            "KandidatId": "489",
            "Stemmer": 66
          }
        ]
      },
      {
        "PartiId": "B",
        "Partistemmer": 300,
        "Kandidater": [
          {
            "KandidatId": "1355",
            "Stemmer": 3
          },
          {
            "KandidatId": "1356",
            "Stemmer": 15
          },
          {
            "KandidatId": "1357",
            "Stemmer": 18
          },
          {
            "KandidatId": "1358",
            "Stemmer": 7
          },
          {
            "KandidatId": "1359",
            "Stemmer": 4
          },
          {
            "KandidatId": "1360",
            "Stemmer": 17
          },
          {
            "KandidatId": "1361",
            "Stemmer": 12
          },
          {
            "KandidatId": "1362",
            "Stemmer": 7
          },
          {
            "KandidatId": "1363",
            "Stemmer": 8
          },
          {
            "KandidatId": "1364",
            "Stemmer": 36
          },
          {
            "KandidatId": "1365",
            "Stemmer": 114
          },
          {
            "KandidatId": "1366",
            "Stemmer": 63
          }
        ]
      },
      {
        "PartiId": "C",
        "Partistemmer": 233,
        "Kandidater": [
          {
            "KandidatId": "2167",
            "Stemmer": 6
          },
          {
            "KandidatId": "2168",
            "Stemmer": 13
          },
          {
            "KandidatId": "2169",
            "Stemmer": 4
          },
          {
            "KandidatId": "2170",
            "Stemmer": 45
          },
          {
            "KandidatId": "2171",
            "Stemmer": 5
          },
          {
            "KandidatId": "2172",
            "Stemmer": 23
          },
          {
            "KandidatId": "2173",
            "Stemmer": 18
          },
          {
            "KandidatId": "2174",
            "Stemmer": 4
          },
          {
            "KandidatId": "2175",
            "Stemmer": 12
          },
          {
            "KandidatId": "2176",
            "Stemmer": 8
          },
          {
            "KandidatId": "2177",
            "Stemmer": 5
          },
          {
            "KandidatId": "2178",
            "Stemmer": 2
          }
        ]
      },
      {
        "PartiId": "D",
        "Partistemmer": 104,
        "Kandidater": [
          {
            "KandidatId": "3041",
            "Stemmer": 3
          },
          {
            "KandidatId": "3042",
            "Stemmer": 14
          },
          {
            "KandidatId": "3043",
            "Stemmer": 0
          },
          {
            "KandidatId": "3044",
            "Stemmer": 2
          },
          {
            "KandidatId": "3045",
            "Stemmer": 9
          }
        ]
      },
      {
        "PartiId": "F",
        "Partistemmer": 417,
        "Kandidater": [
          {
            "KandidatId": "3695",
            "Stemmer": 7
          },
          {
            "KandidatId": "3696",
            "Stemmer": 10
          },
          {
            "KandidatId": "3697",
            "Stemmer": 43
          },
          {
            "KandidatId": "3698",
            "Stemmer": 13
          },
          {
            "KandidatId": "3699",
            "Stemmer": 34
          },
          {
            "KandidatId": "3700",
            "Stemmer": 2
          },
          {
            "KandidatId": "3701",
            "Stemmer": 3
          },
          {
            "KandidatId": "3702",
            "Stemmer": 68
          },
          {
            "KandidatId": "3703",
            "Stemmer": 7
          },
          {
            "KandidatId": "3704",
            "Stemmer": 1
          },
          {
            "KandidatId": "3705",
            "Stemmer": 332
          },
          {
            "KandidatId": "3706",
            "Stemmer": 5
          }
        ]
      },
      {
        "PartiId": "I",
        "Partistemmer": 480,
        "Kandidater": [
          {
            "KandidatId": "4521",
            "Stemmer": 38
          },
          {
            "KandidatId": "4522",
            "Stemmer": 27
          },
          {
            "KandidatId": "4523",
            "Stemmer": 4
          },
          {
            "KandidatId": "4524",
            "Stemmer": 2
          },
          {
            "KandidatId": "4525",
            "Stemmer": 9
          },
          {
            "KandidatId": "4526",
            "Stemmer": 4
          },
          {
            "KandidatId": "4527",
            "Stemmer": 7
          },
          {
            "KandidatId": "4528",
            "Stemmer": 114
          },
          {
            "KandidatId": "4529",
            "Stemmer": 6
          }
        ]
      },
      {
        "PartiId": "K",
        "Partistemmer": 18,
        "Kandidater": [
          {
            "KandidatId": "5268",
            "Stemmer": 0
          },
          {
            "KandidatId": "5269",
            "Stemmer": 3
          },
          {
            "KandidatId": "5270",
            "Stemmer": 4
          },
          {
            "KandidatId": "5271",
            "Stemmer": 1
          },
          {
            "KandidatId": "5272",
            "Stemmer": 0
          }
        ]
      },
      {
        "PartiId": "M",
        "Partistemmer": 668,
        "Kandidater": [
          {
            "KandidatId": "5811",
            "Stemmer": 24
          },
          {
            "KandidatId": "5812",
            "Stemmer": 15
          },
          {
            "KandidatId": "5813",
            "Stemmer": 20
          },
          {
            "KandidatId": "5814",
            "Stemmer": 1
          },
          {
            "KandidatId": "5815",
            "Stemmer": 4
          },
          {
            "KandidatId": "5816",
            "Stemmer": 31
          },
          {
            "KandidatId": "5817",
            "Stemmer": 10
          },
          {
            "KandidatId": "5818",
            "Stemmer": 13
          },
          {
            "KandidatId": "5819",
            "Stemmer": 60
          }
        ]
      },
      {
        "PartiId": "O",
        "Partistemmer": 88,
        "Kandidater": [
          {
            "KandidatId": "6366",
            "Stemmer": 7
          },
          {
            "KandidatId": "6367",
            "Stemmer": 2
          },
          {
            "KandidatId": "6368",
            "Stemmer": 5
          },
          {
            "KandidatId": "6369",
            "Stemmer": 0
          },
          {
            "KandidatId": "6370",
            "Stemmer": 4
          },
          {
            "KandidatId": "6371",
            "Stemmer": 9
          }
        ]
      },
      {
        "PartiId": "Q",
        "Partistemmer": 25,
        "Kandidater": [
          {
            "KandidatId": "6895",
            "Stemmer": 8
          },
          {
            "KandidatId": "6896",
            "Stemmer": 1
          },
          {
            "KandidatId": "6897",
            "Stemmer": 1
          },
          {
            "KandidatId": "6898",
            "Stemmer": 0
          },
          {
            "KandidatId": "6899",
            "Stemmer": 2
          },
          {
            "KandidatId": "6900",
            "Stemmer": 0
          },
          {
            "KandidatId": "6901",
            "Stemmer": 5
          },
          {
            "KandidatId": "6902",
            "Stemmer": 25
          }
        ]
      },
      {
        "PartiId": "V",
        "Partistemmer": 410,
        "Kandidater": [
          {
            "KandidatId": "7442",
            "Stemmer": 40
          },
          {
            "KandidatId": "7443",
            "Stemmer": 20
          },
          {
            "KandidatId": "7444",
            "Stemmer": 20
          },
          {
            "KandidatId": "7445",
            "Stemmer": 1
          },
          {
            "KandidatId": "7446",
            "Stemmer": 5
          },
          {
            "KandidatId": "7447",
            "Stemmer": 55
          },
          {
            "KandidatId": "7448",
            "Stemmer": 90
          },
          {
            "KandidatId": "7449",
            "Stemmer": 70
          },
          {
            "KandidatId": "7450",
            "Stemmer": 15
          },
          {
            "KandidatId": "7451",
            "Stemmer": 3
          },
          {
            "KandidatId": "7452",
            "Stemmer": 0
          },
          {
            "KandidatId": "7453",
            "Stemmer": 0
          }
        ]
      },
      {
        "PartiId": "Æ",
        "Partistemmer": 147,
        "Kandidater": [
          {
            "KandidatId": "9121",
            "Stemmer": 4
          },
          {
            "KandidatId": "9122",
            "Stemmer": 24
          }
        ]
      },
      {
        "PartiId": "Ø",
        "Partistemmer": 382,
        "Kandidater": [
          {
            "KandidatId": "9647",
            "Stemmer": 2
          },
          {
            "KandidatId": "9648",
            "Stemmer": 21
          },
          {
            "KandidatId": "9649",
            "Stemmer": 2
          },
          {
            "KandidatId": "9650",
            "Stemmer": 1
          },
          {
            "KandidatId": "9651",
            "Stemmer": 5
          },
          {
            "KandidatId": "9652",
            "Stemmer": 7
          },
          {
            "KandidatId": "9653",
            "Stemmer": 13
          },
          {
            "KandidatId": "9654",
            "Stemmer": 18
          },
          {
            "KandidatId": "9655",
            "Stemmer": 13
          },
          {
            "KandidatId": "9656",
            "Stemmer": 2
          },
          {
            "KandidatId": "9657",
            "Stemmer": 175
          },
          {
            "KandidatId": "9658",
            "Stemmer": 118
          }
        ]
      },
      {
        "PartiId": "Å",
        "Partistemmer": 280,
        "Kandidater": [
          {
            "KandidatId": "8393",
            "Stemmer": 3
          },
          {
            "KandidatId": "8394",
            "Stemmer": 8
          },
          {
            "KandidatId": "8395",
            "Stemmer": 0
          },
          {
            "KandidatId": "8396",
            "Stemmer": 43
          },
          {
            "KandidatId": "8397",
            "Stemmer": 254
          },
          {
            "KandidatId": "8398",
            "Stemmer": 12
          },
          {
            "KandidatId": "8399",
            "Stemmer": 3
          },
          {
            "KandidatId": "8400",
            "Stemmer": 4
          },
          {
            "KandidatId": "8401",
            "Stemmer": 7
          },
          {
            "KandidatId": "8402",
            "Stemmer": 4
          },
          {
            "KandidatId": "8403",
            "Stemmer": 9
          },
          {
            "KandidatId": "8404",
            "Stemmer": 18
          },
          {
            "KandidatId": "8405",
            "Stemmer": 13
          }
        ]
      }
    ],
    "KandidaterUdenforParti": []
  }
}