{
  "Valgresultater": {
    "AfstemningsomraadeId": "701416",
    "Optaellingstype": "Foreløbig",
    "IndenforParti": [
      {
        "PartiId": "V",
        "Partistemmer": 873,
        "Kandidater": []
      },
      {
        "PartiId": "M",
        "Partistemmer": 30,
        "Kandidater": []
      },
      {
        "PartiId": "C",
        "Partistemmer": 106,
        "Kandidater": []
      },
      {
        "PartiId": "Ø",
        "Partistemmer": 143,
        "Kandidater": []
      },
      {
        "PartiId": "Å",
        "Partistemmer": 2,
        "Kandidater": []
      },
      {
        "PartiId": "O",
        "Partistemmer": 199,
        "Kandidater": []
      },
      {
        "PartiId": "A",
        "Partistemmer": 1540,
        "Kandidater": []
      },
      {
        "PartiId": "F",
        "Partistemmer": 140,
        "Kandidater": []
      },
      {
        "PartiId": "I",
        "Partistemmer": 308,
        "Kandidater": []
      }
    ],
    "KandidaterUdenforParti": []
  }
}